{
  "Timestamp": "2026-02-24T04:02:13Z",
  "date": "2026-02-23",
  "items": [
    {
      "name": "Jam",
      "percent": 150
    },
    {
      "name": "Board",
      "percent": 149
    },
    {
      "name": "Writer",
      "percent": 116
    },
    {
      "name": "Phone",
      "percent": 116
    },
    {
      "name": "Potion",
      "percent": 98
    },
    {
      "name": "Pinata",
      "percent": 96
    },
    {
      "name": "Gnome",
      "percent": 90
    },
    {
      "name": "Easel",
      "percent": 56
    }
  ]
}